[
 {
  "date": "Thu, 31 Dec 2020 01:36:20", 
  "link": "https://www.smzdm.com/p/28666146/", 
  "description": "值友6367968172资料夹学生试卷夹板办公用品~天猫商城此款目前活动售价18.6元，下单使用10元优惠券，实付低至8.6元包邮，近期好价，感兴趣的值友可以入手。", 
  "title": "fizz 飞兹 FZ006382 A4马赛文件夹 8.6元包邮（需用券）"
 }, 
 {
  "date": "Thu, 31 Dec 2020 13:00:00", 
  "link": "https://www.smzdm.com/p/28655678/", 
  "description": "中老年人受到年龄和健康状况的限制，能够购买的重大疾病保险产品和保障额度都比较有限，且往往保费相对较高，这种情况下，如果比较在意癌症风险，可以考虑购买长期防癌险产品。与防癌医疗险不同，防癌险属于特种疾病的重疾险产品，确诊一次性赔付。&gt;&gt;投保问题可点击进入1v1在线咨询&...", 
  "title": "昆仑长期防癌险  保障至80岁/终身 60周岁可投保，116元/年起"
 }, 
 {
  "date": "Thu, 31 Dec 2020 13:00:00", 
  "link": "https://www.smzdm.com/p/28619800/", 
  "description": "zhiaa有效期至2021年3月15日，不约/约不上可退全款。荟集生活现有宁波春晓世茂希尔顿逸林酒店逸林客房2晚度假套餐（含早餐），价格为699元/2晚，有效期至2021年3月15日，元旦/周末不加价，春节2月13日-15日需补差价150元/晚，不约/约不上可退全款。酒店介绍宁波春晓世茂希...", 
  "title": "元旦/周末不加价！宁波春晓世茂希尔顿逸林酒店逸林客房2晚度假套餐（含早餐） 699元/2晚"
 }, 
 {
  "date": "Thu, 31 Dec 2020 00:54:22", 
  "link": "https://www.smzdm.com/p/28665615/", 
  "description": "狗嘿嘿合34.36元/件~京东秒杀价73.9元，可参加满299元减150元店铺活动，叠加京东PLUS会员200-10全品类券，合理凑单可低至34.36元/件。近期好价，感兴趣的值友可以入手。", 
  "title": "京东PLUS会员：Tender Plus 天谱乐食 M3菲力原切牛排净重 150g 73.9元，可低至34.36元"
 }, 
 {
  "date": "Thu, 31 Dec 2020 11:42:40", 
  "link": "https://www.smzdm.com/p/28676564/", 
  "description": "rencaishiwo简单操作，美味不简单。天猫美的好朋友专卖店预告，1号开始抢购，前300件到手价49元，有需要的值友可以看看。", 
  "title": "1日0点：Midea 美的 MC-JK26Simple101 电饼铛 49元包邮（需前300名）"
 }, 
 {
  "date": "Thu, 31 Dec 2020 12:45:48", 
  "link": "https://www.smzdm.com/p/28679514/", 
  "description": "杰克生智能矢量双变频，360°双循环风冷，容E云智能技术。京东自营预售活动，预付20元定金，1日到手价3399元，前50名下单赠1000元E卡，价格低至2399元，感兴趣的值友不容错过~", 
  "title": "23:30截止、1日预售：Ronshen 容声 BCD-650WD12HPA  对开门冰箱 650L 3399元包邮（需定金，前50名低至2399）"
 }, 
 {
  "date": "Thu, 31 Dec 2020 11:42:35", 
  "link": "https://www.smzdm.com/p/28676523/", 
  "description": "rencaishiwo无油烘培，旋钮定时，匀火受热。天猫美的佛山专卖店现在预告，1号开始抢购，前300件到手价154元，有需要的值友可以看看。", 
  "title": "1日0点：Midea 美的 MF-KZ30E201 空气炸锅 3L 154元包邮（需前300件）"
 }, 
 {
  "date": "Wed, 30 Dec 2020 23:20:15", 
  "link": "https://www.smzdm.com/p/28664068/", 
  "description": "Concertos简约精致，便捷办公~天猫liyo立优旗舰店目前售价2.99元包邮，近期好价，进口米白卡纸，书写不透更顺滑，横线设计，便于备忘，感兴趣的值友可以关注一下。", 
  "title": "立优 2021年 卡通台历 多款可选 2.99元包邮"
 }
]