[
 {
  "date": "Sun, 03 Jan 2021 06:21:10", 
  "link": "https://www.smzdm.com/p/28754834/", 
  "description": "樂艺哟合20.92元/件。京东目前售价28.8元，2件9折，下单3件，叠加满79-15元优惠券，实付62.76元，合20.92元/件，喜欢的值友可以关注一下～", 
  "title": "Dove 德芙 巧克力 摩卡榛仁味 243g *3件 62.76元（双重优惠）"
 }, 
 {
  "date": "Sun, 03 Jan 2021 13:37:31", 
  "link": "https://www.smzdm.com/p/28764165/", 
  "description": "值助手折合67.88元/件，防护雾霾和粉尘，汽车尾气，花粉～京东目前售价89元，下单6件95折，叠加80元优惠券，plus会员20元优惠券，实付407.3元包邮，折合67.88元/件，感兴趣的值友们可关注下～", 
  "title": "京东PLUS会员：3M 9501V+ KN95 带呼吸阀口罩 15只 *6件 407.3元包邮（需用券，合67.88元/件）"
 }, 
 {
  "date": "Sun, 03 Jan 2021 09:49:27", 
  "link": "https://www.smzdm.com/p/28757375/", 
  "description": "小值机器人快速结团, 低粉尘, 天然原料, 可冲厕所京东PLUS售价89.9元，下单3件参加满199立减40、可领取满199元7.5折优惠券的促销活动，实付162.27元，折合54.09元/件，近期好价，有需要的选购。", 
  "title": "京东PLUS会员：FUWAN 福丸 玉米豆腐猫砂 2.5kg*4包 *3件 162.27元（合54.09元/件）"
 }, 
 {
  "date": "Sun, 03 Jan 2021 13:54:30", 
  "link": "https://www.smzdm.com/p/28764613/", 
  "description": "王王同学2.1声道家庭值选~拼多多目前官方补贴价为1486元包邮，适合电影，游戏使用，低音效果很震撼，音场很宽，氛围感很强。适配的线材足够长，可以任意摆放，不用担心线长的问题。", 
  "title": "百亿补贴：BOSE Companion 50 多媒体音箱 1486元包邮"
 }, 
 {
  "date": "Sat, 02 Jan 2021 21:23:30", 
  "link": "https://www.smzdm.com/p/28748668/", 
  "description": "值友1781064511辅助矫正书写姿势~京东目前售价39.9元，可参加3件7折活动，下单5件 ，叠加满199减100元优惠券，到手价39.65元， 合7.93元/件，近期好价，感兴趣的值友可以入手。", 
  "title": "Guangbo 广博 H05728 三角杆HB铅笔凹凹笔 50支装 *5件 39.65元（需用券，合7.93元/件）"
 }, 
 {
  "date": "Sun, 03 Jan 2021 13:27:27", 
  "link": "https://www.smzdm.com/p/28763926/", 
  "description": "喵小达兼容苹果及主流安卓、1分钟降温14度。拼多多售价159元，黑卡可抵扣23.85元，到手价135.15元，可有效解决手机发热问题，近期好价，感兴趣的值友可以入手。", 
  "title": "BLACK SHARK 黑鲨 冰封散热背夹 Pro 159元包邮（黑卡可抵23.85元）"
 }, 
 {
  "date": "Sun, 03 Jan 2021 09:17:19", 
  "link": "https://www.smzdm.com/p/28756709/", 
  "description": "Mothorchid保暖舒适天猫精选现售价99.9元，领取40元优惠券，到手价59.9元，近期好价，感兴趣的值友可以入手。", 
  "title": "me feeling MFNY02 男士自发热保暖内衣套装 59.9元包邮（需用券）"
 }, 
 {
  "date": "Sun, 03 Jan 2021 00:14:31", 
  "link": "https://www.smzdm.com/p/28751560/", 
  "description": "chromesR5 Pro 4650U处理器，400尼特高色域1月4日，京东自营秒杀价为5199元，持平上次首页推荐价格，R5 Pro 4650U确保运行速度行云流水，无论生产娱乐皆无忧，感兴趣的值友不妨关注下~", 
  "title": "4日0点：HP 惠普 战X 锐龙版 15.6英寸笔记本电脑（R5 Pro 4650U、16GB、512GB） 5199元包邮"
 }, 
 {
  "date": "Sun, 03 Jan 2021 10:03:10", 
  "link": "https://www.smzdm.com/p/28757811/", 
  "description": "一朵浪花儿超韧细密，湿水不易破~京东1月4日10点售价19.9元，限量抢购，大家可以试试~", 
  "title": "4日10点、运费券收割机：Vinda 维达 超韧系列 木浆无芯卷纸 4层*78g*30卷 112*146mm 19.9元"
 }, 
 {
  "date": "Sun, 03 Jan 2021 11:43:24", 
  "link": "https://www.smzdm.com/p/28760867/", 
  "description": "划船不用Jiang收纳方便，厚实耐用～京东百露官方旗舰店此商品目前售价12元，下单5件，购物车换促销参与满3件打7折活动，领取满60-14元优惠券，28元包邮到手5件，折合5.6元/件。近期好价，如果有需要就买它。", 
  "title": "BELO 百露 桌面塑料收纳盒 小号 *5件 28元包邮（需用券，合5.6元/件）"
 }, 
 {
  "date": "Sun, 03 Jan 2021 10:57:11", 
  "link": "https://www.smzdm.com/p/28759477/", 
  "description": "墨问莫子涵丶防风防水，鹅绒填充保暖羽绒大衣天猫目前售价8800元，近期好价，感兴趣的值友可以入手", 
  "title": "ARC'TERYX 始祖鸟 GORE-TEX 防水 THERME PARKA   男子羽绒服 8800元包邮"
 }, 
 {
  "date": "Sun, 03 Jan 2021 13:15:09", 
  "link": "https://www.smzdm.com/p/28763578/", 
  "description": "发烧值友推荐添加FOS果寡糖&维生素E~天猫波奇网旗舰店目前售价79.9元，参与店铺满1件8折促销活动，叠加25元优惠券，实付38.92元包邮，感兴趣的值友们可关注下～", 
  "title": "Wanpy 顽皮 小金罐 白肉猫罐头 85g*12罐 38.92元包邮（需用券）"
 }, 
 {
  "date": "Sat, 02 Jan 2021 21:48:17", 
  "link": "https://www.smzdm.com/p/28748992/", 
  "description": "小小值机器人福运“菲”凡～天猫商城该商品正在热销，最终到手价9.9元/件，喜欢可入。", 
  "title": "FILORGA 菲洛嘉 1月会员专属福袋尝鲜体验礼 9.9元包邮"
 }, 
 {
  "date": "Sun, 03 Jan 2021 09:16:20", 
  "link": "https://www.smzdm.com/p/28756669/", 
  "description": "被窝里的小可爱保暖舒适天猫精选现售价74.9元，领取55元优惠券，到手价19.9元，近期好价，感兴趣的值友可以入手。", 
  "title": "AL203 24214302 男女款保暖内衣 19.9元包邮（需用券)"
 }, 
 {
  "date": "Sun, 03 Jan 2021 09:59:33", 
  "link": "https://www.smzdm.com/p/28757731/", 
  "description": "秋风好酷营养丰富~京东PLUS会员专享价575元，参加满199元减100元活动，使用满299减150券，实付325元包邮，近期好价，有需需要的选购。", 
  "title": "京东PLUS会员：SINGEN 发育宝 幼猫粮 冻干粮 8kg 325元（需用券）"
 }, 
 {
  "date": "Sun, 03 Jan 2021 13:18:37", 
  "link": "https://www.smzdm.com/p/28763654/", 
  "description": "迷茫中潜行简约百搭唯品会 售价599元，页面领取20元优惠券，到手价579元包邮，多款式可选，喜欢可入～", 
  "title": "CHJ JEWELLERY 潮宏基 祝福系列 文字黄金吊坠 579元包邮（需用券）"
 }, 
 {
  "date": "Sun, 03 Jan 2021 13:49:12", 
  "link": "https://www.smzdm.com/p/28764444/", 
  "description": "售罄不易褪色,不起球～天猫garysoon童装旗舰店售价19.99元，领取3元优惠券，实际到手价16.99元包邮，喜欢的值友可以入手～", 
  "title": "Garysoon 儿童加绒保暖内衣套装 16.99元包邮（需用券）"
 }, 
 {
  "date": "Sun, 03 Jan 2021 07:41:27", 
  "link": "https://www.smzdm.com/p/28755371/", 
  "description": "AC220轻量化设计 保暖兼顾透气 版型简洁干练京东商城售价99元，1件6折，下单2件使用价格下方满159元减40元优惠券，实付78.8元，折合39.4元/件，近期好价，如果需要就买它", 
  "title": "Pelliot 伯希和 11631101 男女款户外抓绒裤 *2件 78.8元包邮（需用券，合39.4元/件）"
 }, 
 {
  "date": "Sat, 02 Jan 2021 23:38:18", 
  "link": "https://www.smzdm.com/p/28751049/", 
  "description": "漂亮的老大妈大翻领设计，活泼可爱。唯品会目前售价159元包邮，尺码齐全，近期好价，需要的关注。", 
  "title": "MONTAGUT 梦特娇  女童毛衣裙子两件套   159元包邮"
 }, 
 {
  "date": "Sun, 03 Jan 2021 12:57:20", 
  "link": "https://www.smzdm.com/p/28763222/", 
  "description": "宝贝15216柠檬清香。京东目前售价13.9元，下单5件享9折优惠，凑单2件中盐（2件5折），使用满79元减15元优惠券，叠京东95折会员，到手价49.1元，合柠檬茶低至9元/件，中盐2元/件，喜欢可入。", 
  "title": "京东PLUS会员：vitasoy 维他奶 维他低糖柠檬茶 250ml*6盒   *5件 +凑单品 49.1元（多重优惠）"
 }, 
 {
  "date": "Sun, 03 Jan 2021 10:47:18", 
  "link": "https://www.smzdm.com/p/28759175/", 
  "description": "值友1834526519造型简约，收纳不同杂物~京东禧天龙专卖店此商品4日0点秒杀价8.5元，下单3件，参与满3件打7折活动，17.85元包邮到手3件，折合5.95元/件。近期好价，如果有需要就买它。", 
  "title": "4日0点：Citylong 禧天龙 带盖收纳盒 26.3*18.5*7.6cm *3件 17.85元包邮（合5.95元/件）"
 }, 
 {
  "date": "Sun, 03 Jan 2021 13:28:21", 
  "link": "https://www.smzdm.com/p/28763913/", 
  "description": "无极良品坚固耐用，长效保温~京东目前售价39.9元，下单2件9折，实付71.82元到手，折合35.91元/件～", 
  "title": "Fuguang 富光 暖家系列 保温壶 2000ml *2件 71.82元（合35.91元/件）"
 }, 
 {
  "date": "Sun, 03 Jan 2021 10:15:14", 
  "link": "https://www.smzdm.com/p/28758109/", 
  "description": "我也叫吴青峰亲肤舒适。天猫精选目前售价149元，初上市价格299，近期好价，值友们关注一下。", 
  "title": "UNIQLO 优衣库 435796 男士休闲窄口牛仔裤 149元"
 }, 
 {
  "date": "Sun, 03 Jan 2021 12:21:32", 
  "link": "https://www.smzdm.com/p/28762234/", 
  "description": "俏皮营养丰富，老少皆宜~天猫超市4日10点售价价49.9元，前1小时2件5折，下单3件，使用140-10元购物券，88vip会员95折，折后实付61.6元，折合每件20.53元，喜欢的朋友们刚需可入……", 
  "title": "4日10点、88VIP：达利园  八宝粥南瓜小米粥 280g*12罐 *3件 61.6元（前1小时）"
 }
]