[
 {
  "date": "Fri, 20 Dec 2019 20:08:23", 
  "link": "https://www.smzdm.com/p/18215424/", 
  "description": "水樱唇爱水泡儿支持266mm显卡、140mm水冷、ATX电源的小机箱。京东银欣旗舰店当前售价249元，一件9折，实付224.1元包邮到手，支持266mm显卡、140mm水冷、ATX电源的小机箱，近期好价。", 
  "title": "SILVER STONE 银欣 SG13B 珍宝13 ITX机箱 224.1元包邮（满减）"
 }, 
 {
  "date": "Fri, 20 Dec 2019 17:15:38", 
  "link": "https://www.smzdm.com/p/18212602/", 
  "description": "皎月KH5000mAh电池，远程协助，给爸妈的孝心机。京东预告21日16点优惠价799元，有感兴趣的值友不妨关注下。", 
  "title": "21日16点：ZTE 中兴 Blade 20 Smart孝心版 智能手机 4GB+128GB 799元包邮"
 }, 
 {
  "date": "Fri, 20 Dec 2019 20:49:35", 
  "link": "https://www.smzdm.com/p/18215821/", 
  "description": "夏秋AND春冬绅士风格，多色可选~亚马逊海外购目前售价89.68元前，prime会员满200元免运费，税费约8.5元，到手99元左右，多色可选，喜欢的值友可以关注。", 
  "title": "Tacther.H Winter Cashmere 男式羊绒围巾 ￥89.68+￥8.5含税直邮（约￥99）"
 }, 
 {
  "date": "Fri, 20 Dec 2019 20:11:41", 
  "link": "https://www.smzdm.com/p/18215466/", 
  "description": "值友7919112706净重仅1KG，接口全面，配置出色。京东预告21日售价7978元包邮，有感兴趣的值友不妨关注下。", 
  "title": "21日0点：VAIO SX14 14英寸 轻薄本 （i5-8265U、8GB、256GB、1KG） 7978元包邮"
 }, 
 {
  "date": "Fri, 20 Dec 2019 21:55:00", 
  "link": "https://www.smzdm.com/p/18216152/", 
  "description": "落叶郁风考拉海购23日活动价2398元，喜欢的值友不容错过~", 
  "title": "23日0点：MAMMUT 猛犸象 徒步系列 1013-00701 男士羽绒服 2398元"
 }, 
 {
  "date": "Fri, 20 Dec 2019 20:13:29", 
  "link": "https://www.smzdm.com/p/18215484/", 
  "description": "专修复印机40mm大驱动单元，黑红配色。天猫微星旗舰店当前售价99元到手，40mm大驱动单元，黑红配色，近期好价。", 
  "title": "msi 微星 DS501 游戏耳机 99元包邮"
 }, 
 {
  "date": "Fri, 20 Dec 2019 00:40:22", 
  "link": "https://www.smzdm.com/p/18198131/", 
  "description": "莎木Q颜色丰富 设计简约 书写流畅~德国知名钢笔品牌凌美（LAMY）狩猎者系列（Safari系列）钢笔，秉承德系的一贯优秀做工，外观设计新颖时尚，并有多种色款，是不少文具控们收藏的必需品。Safari系列是其经典款，ABS笔杆材质，笔触顺滑。F写中文略粗，但触纸非常顺滑。作为设计质感出...", 
  "title": "LAMY 凌美 Safari 狩猎系列 F尖钢笔 亮黑色 *2件 158.4元包邮（合79.2元/件）"
 }, 
 {
  "date": "Fri, 20 Dec 2019 20:41:28", 
  "link": "https://www.smzdm.com/p/18215730/", 
  "description": "小斌张嘎十代i5+2G独显，1.74Kg轻薄本。京东当前售价4299元，有感兴趣的值友不妨关注下。", 
  "title": "HP 惠普 星15 青春版 15.6英寸笔记本电脑（i5-10210U、8GB、512GB、MX130） 4299元包邮"
 }, 
 {
  "date": "Fri, 20 Dec 2019 18:32:20", 
  "link": "https://www.smzdm.com/p/18214080/", 
  "description": "AD哥独特星星设计，中底带闪光设计。天猫精选该商品售价249元，参加3件8折活动，每件低至200元，包邮，有需要的朋友可以考虑入手~", 
  "title": "SKECHERS 斯凯奇 10920L 大童魔术贴闪灯鞋 低至200元"
 }, 
 {
  "date": "Fri, 20 Dec 2019 20:13:34", 
  "link": "https://www.smzdm.com/p/18215486/", 
  "description": "值友2953714362环保EVA材质，抗压防水耐磨，大号更大容量~京东预告21日16点秒杀价39.9元，有需要的值友可以关注。", 
  "title": "21日16点：Folgemir 跟我来 EVA浮雕文具盒 福兔大款 15*22cm 39.9元"
 }, 
 {
  "date": "Fri, 20 Dec 2019 21:50:41", 
  "link": "https://www.smzdm.com/p/18216266/", 
  "description": "小莉莉大颖颖低至3.4-3.6元/斤~拼多多生鲜万人团～不知道买啥？那再举个栗子～低至3.4-3.6元/斤，单件包邮～首页高人气金鲳鱼/白鲳鱼组合、力度升级的哈尔滨红肠、肯德基咖啡以及 苏宁生鲜大促，也可按需选择丫～2019新鲜栗子板栗5斤，售价18.1元，单件包邮，折合3.6元/斤，下单3...", 
  "title": "举个栗子：玉保 2019新鲜栗子板栗5斤 18.1元"
 }, 
 {
  "date": "Fri, 20 Dec 2019 16:46:50", 
  "link": "https://www.smzdm.com/p/18211879/", 
  "description": "雀斑怪蜀黍亚马逊中国特价至0.99元，喜欢的朋友可以看看。", 
  "title": "《艽野尘梦》 Kindle电子书 0.99元"
 }
]