[
 {
  "date": "Sun, 10 May 2020 22:01:07", 
  "link": "https://www.smzdm.com/p/20965812/", 
  "description": "我是云云干湿双剃，3D浮动贴面，高转速马达，风驰切剃系统，自研磨系统。小米有品目前售价149元，领取30元优惠劵，实付119元，近期好价，感兴趣的值友不容错过~", 
  "title": "PHILIPS 飞利浦 S1203  电动剃须刀 119元包邮（需用券）"
 }, 
 {
  "date": "Mon, 11 May 2020 02:28:40", 
  "link": "https://www.smzdm.com/p/20970441/", 
  "description": "jerichowu合2.26元/瓶~京东目前售价47.9元，下单5件立减40元，叠加满169-30元优惠券，实付169.5元，合33.9元/件，喜欢的值友可以关注一下~", 
  "title": "Watsons 屈臣氏 新奇士橙汁汽水 380ml*15瓶 *5件 169.5元（双重优惠）"
 }, 
 {
  "date": "Mon, 11 May 2020 02:10:37", 
  "link": "https://www.smzdm.com/p/20970376/", 
  "description": "永恒之星-龙京东目前49.9元每件，下单5件打9折，叠加229减40券，实付184.55元，合36.91元/件，好价~", 
  "title": "雪龙瑞斯 优选稻花香米 东北大米 5kg *5件 184.55元（双重优惠）"
 }, 
 {
  "date": "Mon, 11 May 2020 00:31:47", 
  "link": "https://www.smzdm.com/p/20969206/", 
  "description": "路人丁丁7.93元/件～京东现价21.5元，下单14件参加满299-150活动，叠加229-40元优惠券，实付111元，合7.93元/件，近期好价，可关注～", 
  "title": "RitterSport 瑞特斯波德玉米片牛奶巧克力 100g *14件 111元（双重优惠）"
 }, 
 {
  "date": "Mon, 11 May 2020 11:16:41", 
  "link": "https://www.smzdm.com/p/20975896/", 
  "description": "闪亮闪亮每件折12.48元，含薄荷成分，使用更清爽~京东超市售价20.8元，参加下单3件总计打6折活动，到手价37.44元，合一件12.48元，可用免邮券带回，喜欢的值友们不要错过~", 
  "title": "Biore 碧柔  男士毛孔清洁黑鼻贴 5片装 *3件 37.44元（合12.48元/件）"
 }, 
 {
  "date": "Mon, 11 May 2020 00:19:14", 
  "link": "https://www.smzdm.com/p/20968851/", 
  "description": "管住自己的手低至45.17元/件京东目前报价64.9元，可参加满2件85折（购物车里修改优惠），买3件叠加满169减30优惠券，买3件实际支付135.5元，折合45.17元/件，入手好价。", 
  "title": "爱氏晨曦 进口全脂纯牛奶 200ml*24盒 *3件 135.5元（双重优惠）"
 }, 
 {
  "date": "Mon, 11 May 2020 10:45:34", 
  "link": "https://www.smzdm.com/p/20974999/", 
  "description": "每件折39.5元，加拿大本土品牌，植物萃取，高保湿~京东国际目前售价79元，下单3件5折，实付118.5元包邮包税，每件折39.5元，有需要的值友可以关注一下～", 
  "title": "Delon 活肤石榴 保湿身体乳 196g *3件 118.5元包邮包税"
 }, 
 {
  "date": "Mon, 11 May 2020 10:31:58", 
  "link": "https://www.smzdm.com/p/20974614/", 
  "description": "Submergence治愈系笑脸钢笔，每日书写好心情～京东商城当前页面价格69.3元，下单3件，参加满149减50元，叠加满99元减25元优惠券，实际到手价132.9元（合44.3元/件）好价精选，可入～叠加优惠券：满99.0元减25.0元", 
  "title": "PILOT 百乐  Kakuno 笑脸透明杆钢笔 F尖（ 配吸墨器+墨胆） *3件 132.9元（需用券，合44.3元/件）"
 }, 
 {
  "date": "Mon, 11 May 2020 11:39:45", 
  "link": "https://www.smzdm.com/p/20976474/", 
  "description": "办公小小值凑单好价~京东商城目前售价42元，下单1件凑单4件橡皮擦享5件5折优惠，实付共低至25元，采用优选材料，易防水，防潮，近期好价，感兴趣的值友可以入手。", 
  "title": "M&G 晨光 ADM95303 DIY多功能文件框 单个装 25元（需凑单）"
 }, 
 {
  "date": "Mon, 11 May 2020 08:03:04", 
  "link": "https://www.smzdm.com/p/20971826/", 
  "description": "豪横三舅复古风格，舒适百搭。天猫精选reebok官方旗舰店售价128元，关注店铺首页领取减10元优惠券，合118元带回，此款商品多色可选，尺码齐全，喜欢的值友可以关注~", 
  "title": "12日0点：Reebok 锐步 COMPLETE2 SE 男女款复古休闲鞋 118元包邮（需用券）"
 }, 
 {
  "date": "Mon, 11 May 2020 00:26:16", 
  "link": "https://www.smzdm.com/p/20969043/", 
  "description": "chromes可折叠榻榻米床垫，干爽透气，有效防螨~京东预告12日0点特价至799元包邮，近期好价，喜欢的朋友可以关注一下～", 
  "title": "12日0点：Aisleep 睡眠博士 天然乳胶标准型床垫 180*200*5cm 799元包邮"
 }, 
 {
  "date": "Sun, 10 May 2020 23:49:58", 
  "link": "https://www.smzdm.com/p/20968377/", 
  "description": "值友69015961583匹变频立柜，1级能效，R32冷媒，WiFi控制。天猫GREE格力官方旗舰店目前售价8999元，参加活动满8999元减1500元，叠加200元优惠劵，实付7299元，近期好价，感兴趣的值友不容错过~", 
  "title": "Gree  格力 KFR-72LW/NhZcB1W  柜机空调 3匹 7299元包邮（双重优惠）"
 }, 
 {
  "date": "Mon, 11 May 2020 00:19:57", 
  "link": "https://www.smzdm.com/p/20968875/", 
  "description": "薯条大宝宝合37.17元/件目前京东报价62.9元，下单3件打75折，叠加169-30优惠券，实付111.52元，折合37.17元/件，好价可以入手。", 
  "title": "伊利 纯牛奶250ml*20盒/箱（礼盒装） *3件 111.52元（双重优惠）"
 }, 
 {
  "date": "Mon, 11 May 2020 01:47:28", 
  "link": "https://www.smzdm.com/p/20970252/", 
  "description": "永恒之星-龙京东目前55.9元每件，下单3件加凑单品鸭脖一包，叠加页面169减30券，实付139.7元，合46.57元/件，好价。", 
  "title": "福临门 东北大米 水晶米 大米 10kg *3件 +凑单品 139.7元（需用券）"
 }, 
 {
  "date": "Mon, 11 May 2020 11:39:15", 
  "link": "https://www.smzdm.com/p/20976521/", 
  "description": "值选好券领取时间2020-05-11 11:39:00 至 2020-05-13 00:00:00领取说明每日京豆福利发布后，会第一时间更新至每日必领专区，值友们可点击首页“每日必领”icon，每天来此领京豆、白条支付券、话费券、外卖红包等福利，下单可抵扣！5月11日店铺关注/签到领京豆...", 
  "title": "移动专享：5月11日 京东关注店铺领京豆 实测领50京豆"
 }, 
 {
  "date": "Mon, 11 May 2020 11:38:41", 
  "link": "https://www.smzdm.com/p/20931264/", 
  "description": "重疾险，顾名思义是保障重大疾病风险。在健康保险分类中，可以分为医疗险和重疾险，一般医疗险为报销型产品，主要承担医疗费用，而重疾险属于给付型保险，一次性赔付后可用于治疗、治疗后恢复，以及补偿因误工导致的经济损失，减轻整个家庭的经济负担。超级玛丽重疾险2020Max 是一款恶性肿瘤、...", 
  "title": "信泰 超级玛丽重疾险2020Max 202元/年起，限时奖励200元京东卡"
 }, 
 {
  "date": "Sun, 10 May 2020 21:56:34", 
  "link": "https://www.smzdm.com/p/20965730/", 
  "description": "qer007磁吸侧板多变风道，展示型电源仓。京东当前满减到手价549元，近期低价，感兴趣的值友可以关注。", 
  "title": "DEEPCOOL 九州风神 魔方550 机箱 白色 549元包邮（下单立减）"
 }, 
 {
  "date": "Mon, 11 May 2020 09:23:05", 
  "link": "https://www.smzdm.com/p/20966251/", 
  "description": "值友1645243883出色降噪，续航持久，差旅好物。拼多多优越数码海外专营店百亿补贴售价1499元包邮，非国行版本，有需要的可关注。", 
  "title": "SONY 索尼 WH-1000XM3 头戴式蓝牙降噪耳机 1499元含税包邮"
 }, 
 {
  "date": "Mon, 11 May 2020 07:49:16", 
  "link": "https://www.smzdm.com/p/20971713/", 
  "description": "honestly激发学习兴趣，提示动手动脑能力~天猫卓学办公专营店售价25.8元，可领取10元优惠券，下单实付低至15.8元包邮；小学初中简单串并联实验器材，多种实验套餐，让孩子实践中学习知识。近期好价，喜欢的值友不容错过~", 
  "title": "可普 小学科学趣味 磁铁实验盒 15.8元包邮（需用券）"
 }, 
 {
  "date": "Mon, 11 May 2020 08:04:28", 
  "link": "https://www.smzdm.com/p/20971846/", 
  "description": "我本善良呀京东特价99元，参加2件九折，叠加169-30的优惠券，下单2件实付148.2元包邮，合74.1元/件，好价~", 
  "title": "农心 辛拉面Black 方便面 101g*16碗 *2件 148.2元包邮（双重优惠）"
 }, 
 {
  "date": "Sun, 10 May 2020 23:18:13", 
  "link": "https://www.smzdm.com/p/20967662/", 
  "description": "cxcgfzhj选用精种水牛大刀毛肚京东目前售价208元，可领取满208-112元优惠券，再领取京东plus会员满200-10元全品类优惠券，到手价格86元。近期好价，喜欢吃毛肚的小伙伴别错过哦。", 
  "title": "京东PLUS会员：唐之味  火锅牛毛肚  1kg/袋 86元（双重优惠）"
 }, 
 {
  "date": "Mon, 11 May 2020 09:20:36", 
  "link": "https://www.smzdm.com/p/20966304/", 
  "description": "值友1645243883音质饱满细腻+消除回音/噪声拼多多优越数码海外专营店百亿补贴价格为639元含税包邮，有蓝色/迷彩色/闪电条纹3色可选，喜欢的值友可以入手了。", 
  "title": "百亿补贴：JBL Charge 3 音乐冲击波 蓝牙音箱 639元含税包邮"
 }, 
 {
  "date": "Mon, 11 May 2020 10:58:23", 
  "link": "https://www.smzdm.com/p/20975350/", 
  "description": "阳光_总在风雨后合15.61元/件~天猫超市该商品当前售价29.9元，买7件，参加满199-100元的活动，合15.61元/件。感兴趣的值友不容错过~", 
  "title": "Three Squirrels 三只松鼠 开心果 100g *7件 109.3元（下单立减）"
 }, 
 {
  "date": "Mon, 11 May 2020 10:55:44", 
  "link": "https://www.smzdm.com/p/20975283/", 
  "description": "似非咯好价可入~天猫商城团客互动食品专营店目前售价18.9元，领取5元优惠券，券后13.9元，折合1.7元/听，全国包邮（偏远地区除外），近期新低，值得买！", 
  "title": "康师傅饮料310ml*8听 5种口味可选（冰红茶/水蜜桃/酸梅汤/冰糖雪梨/水晶葡萄） 13.9元（需用券）"
 }, 
 {
  "date": "Mon, 11 May 2020 00:27:33", 
  "link": "https://www.smzdm.com/p/20969094/", 
  "description": "大秦武士方便美味。目前京东售价29.8元，下单6件参加75折活动再叠加30元优惠券，实付104.1元包邮，合17.35元/件，喜欢可入。", 
  "title": "小猪呵呵 火腿猪肉罐头 340g *6件 104.1元包邮（双重优惠）"
 }, 
 {
  "date": "Mon, 11 May 2020 11:37:04", 
  "link": "https://www.smzdm.com/p/20976450/", 
  "description": "值选好券领取限制5积分兑换每人限领1次领取时间2020-05-11 00:00:00 至 2020-05-12 00:00:00领取说明1、优惠额度：满99减25元优惠券；2、使用时间：5月11日00：00-5月11日23:59；3、适用范围：京东自营文具品类部分商品4、可叠加京东站内每...", 
  "title": "京东自营文具品类 满99-25优惠券 可叠加每满149-50，叠后力度低至5折 满99-25元"
 }, 
 {
  "date": "Sun, 10 May 2020 21:57:40", 
  "link": "https://www.smzdm.com/p/20965751/", 
  "description": "南北桃源全合成机油京东商城目前报价498，凑单两件凑单品后可用plus每日可领的20元全品券，实付480元两次保养，需要的值友可关注。叠加优惠券：1元凑单", 
  "title": "车享家 嘉实多 磁护 5W-40 全合成保养卡 2次 含机油+工时+洗车 480元包安装（需用券）"
 }, 
 {
  "date": "Mon, 11 May 2020 11:06:09", 
  "link": "https://www.smzdm.com/p/20975608/", 
  "description": "绿色环保EVA材质，舒适好打理不粘发~天猫商城玖居家居专营店售价19.9元，可领取10元优惠券，下单实付低至9.9元包邮；这款防滑垫能有效解决地滑问题，近期好价，感兴趣的值友可以入手。", 
  "title": "ENGMARSS 英玛仕 浴室厕所防滑垫 60*40cm 9.9元包邮（需用券）"
 }, 
 {
  "date": "Mon, 11 May 2020 07:50:17", 
  "link": "https://www.smzdm.com/p/20971723/", 
  "description": "honestly20支针管笔芯+1支中性笔好价~格立思全针管笔芯，简约设计，大容量，书写顺滑。格立思家的针管，内径升级，油墨加量更实惠；超长书写，全长130m，通用长度90mm墨量，可视窗口，墨量看得见；不锈钢钨珠笔头不掉珠，3色可选。天猫大淘办公专营店目前售价7.9元，下单领满7元减1元优惠券...", 
  "title": "格立思 GLS-01 20支针管笔芯+1支中性笔 6.9元（需用券）"
 }, 
 {
  "date": "Mon, 11 May 2020 11:36:52", 
  "link": "https://www.smzdm.com/p/20976322/", 
  "description": "家居家装小值君整个夏天，凉爽好睡眠~京东此款预告12日好价，到手价99元，三件套好价", 
  "title": "12日0点：水星家纺  晨慕 印花冰丝席三件套 180*200cm 99元包邮"
 }
]