[
 {
  "date": "Sat, 09 Dec 2017 13:30:00", 
  "link": "https://www.smzdm.com/p/8298100/", 
  "description": "3C家电小小值现在这个时代最火的娱乐方式是什么？当然是游戏了啊——上到爷爷辈儿的用手机斗地主偷菜打麻将，下到咿呀学语的婴孩也在iPad上划拉着学习认字和物体，连小学生都从英雄联盟到王者荣耀玩了个遍。与之相对应的产业也日渐发达，短短数年之内就从“你要是去玩游戏就打死你”到“你玩这个游戏是不是职业...", 
  "title": "《Hi-Fi控》No.17：电子竞技需要听力 还有一副好耳机"
 }, 
 {
  "date": "Sat, 09 Dec 2017 13:29:52", 
  "link": "https://www.smzdm.com/p/8324567/", 
  "description": "经典501系列，休闲百搭款，近期好价可入。西集网特价至199元包邮，国内现货，下单即发，多尺码可选，经典直筒款式，近期好价。", 
  "title": "Levi's 李维斯 501系列 501-0537 男士直筒牛仔裤 199元包邮"
 }, 
 {
  "date": "Sat, 09 Dec 2017 13:28:12", 
  "link": "https://www.smzdm.com/p/8323342/", 
  "description": "简约设计，结构稳固，方便实用~国美好事达家具旗舰店目前售价49元包邮，适合单人自用或放置在出租屋内使用，简约方便，需要的值友可以入手。", 
  "title": "Homestar 好事达 1461 简易台式电脑桌  49元包邮（需用券）"
 }, 
 {
  "date": "Sat, 09 Dec 2017 11:41:38", 
  "link": "https://www.smzdm.com/p/8326444/", 
  "description": "橡树先生树熟冷冻，肉厚无核，折后27.93元/件~京东目前售价39.9元，限购4件，可用生鲜满199-60券，下单折27.93元/件。此款是无核冷冻树熟榴莲，纯榴莲肉，喜欢的值友不要错过。限北京、上海、天津、福建、湖北、湖南、广东、陕西地区。", 
  "title": "限地区：THAI AO CHI 泰奥琪 冷冻榴莲(无核) 250g盒装 39.9元，可满199-60"
 }, 
 {
  "date": "Sat, 09 Dec 2017 11:25:49", 
  "link": "https://www.smzdm.com/p/8326138/", 
  "description": "值友7718133173天猫scenekid数码旗舰店 现有苹果/vivoy/魅族钢化膜，原价4.9元，使用3元优惠券后，1.9元包邮到手，近期好价。商品页显示，下单还送指环支架，不放心的值友，可以再咨询商家。", 
  "title": "SCENEKID 苹果/vivoy/魅族钢化膜 非全屏 送指环支架 1.9元包邮（需用券）"
 }
]