[
 {
  "date": "Wed, 31 Oct 2018 18:55:32", 
  "link": "https://www.smzdm.com/p/11273032/", 
  "description": "个护钟表小小值全新Autobahn系列，搭载独创Neomatik自动机芯，包豪斯设计风格，极简大气~NOMOS京东自营旗舰店现售价35899元，1日0点开始，可参与每满1000-150元满减活动，再叠加价格下方满1999-300元优惠券，最终实付34099元包邮到手，感兴趣的值友们千万不要错过...", 
  "title": "1日0点、新品发售：NOMOS 诺莫斯  Autobahn系列 1303 男士机械腕表 34099元包邮（双重优惠）"
 }, 
 {
  "date": "Wed, 31 Oct 2018 18:55:10", 
  "link": "https://www.smzdm.com/p/11273383/", 
  "description": "办公小小值活动时间：11月1日0点，京东投影仪品类限时秒杀。活动内容及力度：商品购买页面可领取1000减50元优惠券，400减50元优惠券，相比于之前的投影品类促销，本次秒杀的力度还是相当给力的。叠加使用50元优惠券，价格更低。秒杀活动涵盖了普通投影仪、办公投影仪、激光电视等，涵盖了投影品...", 
  "title": "1日0点、双11预售：京东11月1日双11预热投影仪好价汇总 爆款投影限时秒杀，可领取50元优惠券"
 }, 
 {
  "date": "Wed, 31 Oct 2018 18:54:52", 
  "link": "https://www.smzdm.com/p/11273357/", 
  "description": "家居日百小小值每999减50元，100元封顶，不少爆款低价入手~苏宁易购高仪官方旗舰店于11月1日0点-2点，爆款商品76折起，可领取每999减50元优惠券，100元封顶活动涵盖：花洒、龙头、马桶、水槽等爆款单品活动时间：11月1日0点-2点好价单品：国内1日0点：GROHE 高仪 36462...", 
  "title": "1日0点、促销活动：苏宁易购 高仪官方旗舰店  限前2小时，爆款商品76折起"
 }, 
 {
  "date": "Wed, 31 Oct 2018 18:54:29", 
  "link": "https://www.smzdm.com/p/11263739/", 
  "description": "双层加绒，冬天不怕冷。天猫神采奕奕居家日用旗舰店促销价16.9元，可使用3元店铺优惠券，实付13.9元包邮到手。3双装近期好价，另有普通款可选，有需要的值友可以囤~叠加优惠券：3元优惠券", 
  "title": "神采奕奕 加绒加长塑胶洗碗手套 3双装 13.9元包邮（需用券）"
 }, 
 {
  "date": "Wed, 31 Oct 2018 18:54:10", 
  "link": "https://www.smzdm.com/p/11267273/", 
  "description": "五月天19972K分辨率、100% sRGB色域，支持FreeSync技术。京东商城11月1日0点秒杀价1888元，近期好价，各位值友可以试下能否使用全品类优惠券做到更低。", 
  "title": "1日0点：HP 惠普 27q 27英寸 PLS显示器（2560×1440、100% sRGB、FreeSync） 1888元包邮（需用券）"
 }, 
 {
  "date": "Wed, 31 Oct 2018 18:31:39", 
  "link": "https://www.smzdm.com/p/11273587/", 
  "description": "锦鲤一尾索大18年新款X9000F系列，55英寸4K，X1进阶版图像处理芯片。新蛋中国目前售价6499元，使用蛋券DJ11可减50元，到手6449元包邮，近期好价。", 
  "title": "SONY 索尼 KD-55X9000F 液晶电视 55英寸 6449元包邮（需用码）"
 }, 
 {
  "date": "Wed, 31 Oct 2018 18:35:32", 
  "link": "https://www.smzdm.com/p/11273645/", 
  "description": "天道酬勤-微信操控，3000W速热，一级能效。京东1号0点到手价1199元包邮，价保11.11，8年包修，感兴趣的可以预约。", 
  "title": "1日0点：Leader 统帅 LEC6003-C3(U1) 电热水器 60L 1199元包邮"
 }, 
 {
  "date": "Wed, 31 Oct 2018 18:53:15", 
  "link": "https://www.smzdm.com/p/11271114/", 
  "description": "前方有狼100%羊毛材质，3色可选~天猫精选蜜桃派官方旗舰店将于11日16点特价至59元包邮，3色可选，S、L码有货，100%羊毛材质，面料舒适保暖，喜欢的值友可以等待变价入手了~", 
  "title": "双11预告、再降价：PEACH JOHN 蜜桃派 1013872 女士羊毛连衣裙 59元包邮"
 }, 
 {
  "date": "Wed, 31 Oct 2018 18:06:27", 
  "link": "https://www.smzdm.com/p/11273238/", 
  "description": "chromes双Micro SD卡槽，可存储海量无损音乐。京东预告1日0点特价至2199元，页面领券1999-500，到手1699元，近期好价", 
  "title": "1日0点： Charm Opus 欧普斯 OPUS 32GB 无损播放器 1699元包邮（需用券）"
 }, 
 {
  "date": "Wed, 31 Oct 2018 18:52:46", 
  "link": "https://www.smzdm.com/p/11270634/", 
  "description": "冬季加厚A水洗棉B珊瑚，高支高密水晶绒法莱绒亚马逊中国这款四件套售价为259元，下单输入优惠码“6E34BBNH”立减70元，到手价189元包邮。近期入手好价，喜欢这种风格的值友可入手。", 
  "title": "婉寇 珊瑚绒四件套 黑白格, 1.5米床适用【被套200*230cm】 189元包邮(需用码）"
 }, 
 {
  "date": "Wed, 31 Oct 2018 18:52:36", 
  "link": "https://www.smzdm.com/p/11273778/", 
  "description": "家居日百小小值陶瓷阀芯，原装进口，主体材料选用铜+镀层。苏宁易购原价599元，11.1日0-2点购买，预计到手价455元包邮，有需要的值友可以入手。", 
  "title": "1日0点：GROHE 高仪 23454000 吉特面盆龙头  455元包邮（限前2小时）"
 }, 
 {
  "date": "Wed, 31 Oct 2018 18:38:43", 
  "link": "https://www.smzdm.com/p/11273699/", 
  "description": "温馨的小猪再降价，单只仅需1.95元~天猫麦天家居旗舰店目前售价10.8元，领取3元优惠券，券后实付7.8元包邮到手，4个装，折合1.95元/只，较上次推荐又有小降，有需要的值友可以关注一下~", 
  "title": "麦田 家用情侣洗漱杯 4个装 7.8元包邮（需用券）"
 }, 
 {
  "date": "Wed, 31 Oct 2018 18:52:09", 
  "link": "https://www.smzdm.com/p/11261778/", 
  "description": "美梦树全面反映清末民初百年沧桑的大型历史画册。京东此书售价304元，参加每满199-100促销活动，还可叠加京东200-80元值友专享券，做到满400-280，凑单到手约合91.2元，折合定价2.9折入手，或者使用京东其他档位优惠券做到更好价格，感兴趣的朋友可以考虑凑单入手。更多活动可...", 
  "title": "《壹玖壹壹：从鸦片战争到军阀混战的百年影像史》 304元，可400-280"
 }, 
 {
  "date": "Wed, 31 Oct 2018 18:52:04", 
  "link": "https://www.smzdm.com/p/11273823/", 
  "description": "办公小小值70克，适合办公、绘画、草稿等~京东齐心办公旗舰店目前售价95元，11月1日0点秒杀价89元，下单4件可使用25元优惠券，下单到手价331元包邮，单件合82.75元，有企业采购需求的用户可以关注一下。", 
  "title": "COMIX 齐心 A4复印纸 70g 500张 5包/箱 *4件 331元包邮（需用券，合82.75元/件）"
 }, 
 {
  "date": "Wed, 31 Oct 2018 18:37:38", 
  "link": "https://www.smzdm.com/p/11273677/", 
  "description": "天道酬勤-三档容量变换，多档节能变温。京东发布预告，11月1日0-1点到手价1899元包邮，享0元安装，送沙宣电吹风，晒安装图送598元刀具+VIP延保卡，需要的朋友现在可以提前预约了。", 
  "title": "1日0点：Midea 美的 JSQ30-G3S 16升 燃气热水器 1899元包邮"
 }, 
 {
  "date": "Wed, 31 Oct 2018 18:51:19", 
  "link": "https://www.smzdm.com/p/11272094/", 
  "description": "3C小小值华米OV统统历史新低，买手机最佳时机到来。一年一度的双11马上就到来，而各大电商早已按耐不住性子，开启了第一波促销。按照往年惯例，11月1日是开启大促的重要日子，活动力度不会亚于双11当天，因此会有不少好价、小神价的产品出现。本次京东和苏宁就分别提前前放出了不少全品券和手机专属优...", 
  "title": "促销活动：双11第一波 智能手机 1日0点好价汇总 Z1最低仅为1198元、小米8 SE历史低价，多档大额优惠券放出"
 }
]