[
 {
  "date": "Thu, 20 Oct 2016 09:28:19", 
  "link": "http://www.smzdm.com/p/6522241/", 
  "description": "值为爆料弩哥款再补货，近期好价~亚马逊海外购目前售价79.95元，加上直邮中国运费和预缴关税35.8元，实付115.75元到手，补货后近期好价，喜欢的剧迷们可以考虑购买。", 
  "title": "McFarlane TOYS 麦克法兰 行尸走肉 拼装系列 Daryl Dixon 机车弩哥 ￥79.95+￥35.8直邮中国（约￥115.75）"
 }, 
 {
  "date": "Thu, 20 Oct 2016 09:27:36", 
  "link": "http://www.smzdm.com/p/6521912/", 
  "description": "无敌俩孩爹买一赠一，三步梯，天板高79cm。亚马逊中国Z秒杀668元，持平历史最低价格，同时还赠送一个SE-3的小梯台，家里换灯泡，拿高处的东西都很方便，需要的值友可入。", 
  "title": "Hasegawa 长谷川 SRA-8 三步安全梯  668元包邮，赠SE-3踏台梯"
 }
]