[
 {
  "date": "Sun, 15 Dec 2019 14:42:30", 
  "link": "https://www.smzdm.com/p/18112863/", 
  "description": "值选好券领取时间2019-12-15 00:00:00 至 2019-12-21 23:59:00领取说明活动介绍：京东神券福利站，每天限量发放白条券和支付券。满49-2元支付券、满49-3元白条券，还有京东支付新用户可领5元无门槛支付券。满20-10元京东自营图书券；活动说明：支付券和...", 
  "title": "京东 免费领满49-2元支付券、满49-3元白条券，每天限量发放 3元白条券亲测已领到"
 }, 
 {
  "date": "Sun, 15 Dec 2019 09:48:34", 
  "link": "https://www.smzdm.com/p/18109346/", 
  "description": "天下第3帅又一个传奇0.95大光圈。卓美网售价54800元，有感兴趣的值友不妨关注下。", 
  "title": "Nikon 尼康 尼克尔 Z 58mm f/0.95 S Noct 标准定焦镜头 54800元包邮"
 }, 
 {
  "date": "Sun, 15 Dec 2019 14:29:19", 
  "link": "https://www.smzdm.com/p/18112657/", 
  "description": "值友4057146738舒适透气，拼团好价~苏宁易购当前2人拼团价格19.9元，多重选择，舒适透气~", 
  "title": "Nan ji ren 南极人 YL-12 男士纯色棉袜 10双装 19.9元包邮（2人拼团）"
 }, 
 {
  "date": "Sun, 15 Dec 2019 14:26:34", 
  "link": "https://www.smzdm.com/p/18112608/", 
  "description": "五月阿信4K投影仪好价~京东目前售价7799元包邮，晒单返100元E卡，赠送电视盒子+3D眼镜，近期好价，有需要的值友可以入手。", 
  "title": "BenQ 明基 TK800M 4K投影仪 7799元包邮，晒单返100元E卡，赠送电视盒子+3D眼镜"
 }, 
 {
  "date": "Sun, 15 Dec 2019 14:41:04", 
  "link": "https://www.smzdm.com/p/18112380/", 
  "description": "值友9678456753长粒香软，折1.7元/斤。京东售价36元，参加满2件打75折活动，叠加页面领取满69元减20元优惠券。直接下单2件实付34元 ，折17元/件。", 
  "title": "五丰 优选丝苗米  5kg *2件 34元（双重优惠）"
 }, 
 {
  "date": "Sun, 15 Dec 2019 14:40:44", 
  "link": "https://www.smzdm.com/p/18074450/", 
  "description": "蓝色妖姬的魅惑红枣与枸杞的经典搭配~天猫超市17日10点售价69.9元，前2000件第2件0元，实付合69.9元包邮，折合34.95元/件，近期好价，有需要的值友可关注~", 
  "title": "17日10点：蒙牛 纯甄 红枣枸杞风味酸牛乳 200g*16包 *2件 69.9元包邮（前2000件）"
 }, 
 {
  "date": "Sun, 15 Dec 2019 14:18:21", 
  "link": "https://www.smzdm.com/p/18112502/", 
  "description": "美丽的jier现代简约，轻奢灰色~该商品目前京东售价599元，领券满500元减50元，下单实付549元，接近此前推荐的价格，刚需可入。", 
  "title": "绅士狗 欧尼顿 轻奢灰色地毯  1.6*2.3米 549元包邮（需用券）"
 }, 
 {
  "date": "Sun, 15 Dec 2019 00:44:22", 
  "link": "https://www.smzdm.com/p/18106775/", 
  "description": "值友2729523727钛钢珠笔头设计，可靠耐用~天猫承拓四海办公用品专营店当前售价15.8元包邮，近期好价，感兴趣的值友可以关注。", 
  "title": "BAOKE 宝克 PC1808 中性笔 0.5mm 黑色 36支/盒 15.8元包邮"
 }
]