[
 {
  "date": "Sun, 24 Jan 2021 01:18:17", 
  "link": "https://www.smzdm.com/p/29462132/", 
  "description": "值友8612312796轻盈设计，足弓承托，开放空间唯品会目前活动价149元包邮，多码可选，近期好价，感兴趣的值友可关注。", 
  "title": "ginoble 基诺浦 儿童加绒加厚学步鞋 149元包邮"
 }, 
 {
  "date": "Sun, 24 Jan 2021 07:08:10", 
  "link": "https://www.smzdm.com/p/29466144/", 
  "description": "小值机器人德国拜耳PC箱体，超静音万向轮。苏宁易购售价279元，参加满199元减100元活动，合179元包邮带回，目前安徽省有货，其他地区可以试试，喜欢的值友可以关注~", 
  "title": "限地区：LEVEL8 地平线8号 LA-1688-14T00 20寸拉杆箱 179元包邮"
 }, 
 {
  "date": "Sat, 23 Jan 2021 23:23:21", 
  "link": "https://www.smzdm.com/p/29460183/", 
  "description": "专修复印机包胶耐摔耐磨，自动锁定京东目前价格为17元，入手好价，需要的可以去看看", 
  "title": "deli 得力 DL3797 包胶自锁钢卷尺 5m*25mm 17元"
 }, 
 {
  "date": "Sun, 24 Jan 2021 04:50:10", 
  "link": "https://www.smzdm.com/p/29463239/", 
  "description": "壮志必凌云蓬松柔软，吸水性强 京东售价50元，下单4件，参加满3件总价7折优惠，叠加领取满199-50元优惠券，实际到手价格90元，折合22.5元/件。近期好价，有需要的值友就购买它。", 
  "title": "SANLI 三利  纯棉A类色织大浴巾  73*142cm 380g *4件 90元（需用券，合22.5元/件）"
 }, 
 {
  "date": "Sun, 24 Jan 2021 09:46:12", 
  "link": "https://www.smzdm.com/p/29468695/", 
  "description": "值友8306989551保暖舒适～苏宁易购目前售价189元，页面领取满189-120元优惠券，预计到手价69元，近期好价，感兴趣的值友可以入手。", 
  "title": "MULINSEN 木林森 HC666 中性款软壳长裤 69元包邮（需用券）"
 }, 
 {
  "date": "Sun, 24 Jan 2021 00:07:27", 
  "link": "https://www.smzdm.com/p/29460812/", 
  "description": "狗嘿嘿种类丰富~京东百草味官方旗舰店目前售价318元，领取满318元减230元优惠券，下单1件，叠加京东PLUS会员200-10全品类券，实付78元包邮。近期好价，感兴趣的值友可以入手。", 
  "title": "京东PLUS会员：Be&Cheery 百草味 坚果大礼包 1832g 78元包邮（双重优惠）"
 }, 
 {
  "date": "Sun, 24 Jan 2021 05:48:11", 
  "link": "https://www.smzdm.com/p/29463633/", 
  "description": "小小值机器人一车两态 3秒变身～ 天猫auldey奥迪双钻旗舰店目前售价44.9元，可领取25元优惠券，券后到手价19.9元包邮，近期好价，感兴趣的值友可以入手。", 
  "title": "AULDEY 奥迪双钻 酷变车队系列玩具 3只装 19.9元包邮（需用券）"
 }, 
 {
  "date": "Sun, 24 Jan 2021 09:45:22", 
  "link": "https://www.smzdm.com/p/29429628/", 
  "description": "无聊小胖1月23日至1月31日/2月1日至2月28日每周六、周日/3月1日至3月31日，用户在永辉超市门店购物（永辉生活门店、超级物种门店不参与），并使用微信支付绑定工商银行卡付款，即可享满60元立减30元优惠，每人每周限享1次优惠，每周2080个名额，先到先得，用完即止。如何玩转信用卡...", 
  "title": "移动专享：工商银行 X 永辉超市 微信支付5折优惠 满60-30元"
 }, 
 {
  "date": "Sat, 23 Jan 2021 21:54:21", 
  "link": "https://www.smzdm.com/p/29458927/", 
  "description": "礼sun轻巧坚韧，顺滑万向轮拉杆箱。京东售价269元，京东PLUS会员售价262元，参加满1件打5折活动，合131.5元包邮带回，喜欢的值友可以关注~", 
  "title": "京东PLUS会员：SWISSMOBILITY 5286-22 万向轮拉杆箱 20英寸 131.5元包邮（满1件5折）"
 }, 
 {
  "date": "Sun, 24 Jan 2021 08:14:11", 
  "link": "https://www.smzdm.com/p/29466907/", 
  "description": "值友7407077408双重门襟，保暖百搭。天猫目前售价539元，下单使用210元优惠券，叠加跨店满减，到手实付299元包邮，近期好价，需要的值友可以入手~", 
  "title": "PEACEBIRD MEN 太平鸟 BWACA4E18 连帽羽绒马甲 299元包邮（双重优惠）"
 }
]