[
 {
  "date": "Mon, 23 Sep 2019 18:46:34", 
  "link": "https://www.smzdm.com/p/16326826/", 
  "description": "值友4069970269无味无烟，安心驱蚊~京东目前售价19.9元，两件五折，实付19.9元（合9.95元/件），需要的可以入手~", 
  "title": "运费券收割机：Raid 雷达 电热蚊香液 3瓶装 共168晚 *2件 19.9元（合9.95元/件）"
 }, 
 {
  "date": "Mon, 23 Sep 2019 19:30:34", 
  "link": "https://www.smzdm.com/p/16326491/", 
  "description": "dl_ming轻量透气，Micro G中底，脚感舒适~考拉海购售价399，买三双，参加三件八折活动，黑卡用户叠加900-160优惠券，实付797.6，折合一双265.87，近期好价。", 
  "title": "UNDER ARMOUR 安德玛  Micro G Pursuit BP 男子网面运动跑步鞋  *3件 797.6元（合265.87元/件）"
 }, 
 {
  "date": "Mon, 23 Sep 2019 19:30:00", 
  "link": "https://www.smzdm.com/p/16242930/", 
  "description": "缆车上岛，鸟瞰大海，部分套餐含专车接送，玩转5大游玩区域。飞猪现有越南芽庄珍珠岛一日游，至12月31可订，选择（夜间门票+往返缆车）套餐，可享最低价成人104元起/人，国庆仅微涨125元起/人。另有含餐、含缆车、含接送机套餐可选，其中珍珠岛门票+往返缆车成人246元起/人。更多套...", 
  "title": "当地玩乐：缆车过海体验！ 越南芽庄珍珠岛一日游（中文服务） 104元起/人"
 }, 
 {
  "date": "Mon, 23 Sep 2019 19:28:46", 
  "link": "https://www.smzdm.com/p/16287175/", 
  "description": "无聊小胖即日起至2019年12月31日，用户开通银联无感支付并绑定62开头银联信用卡，在中国石化、冠德石油加油，可享受9折优惠（20元封顶），每月限量30000个，每人每月可享4次，先到先得，用完即止。如何玩转信用卡？什么理财值得投？保险又是哪家强？还请各位多多关注什么值得买（SMZDM...", 
  "title": "移动端：银联  无感支付加油优惠 9折，封顶20元"
 }, 
 {
  "date": "Mon, 23 Sep 2019 19:29:01", 
  "link": "https://www.smzdm.com/p/16326817/", 
  "description": "思思妹213针织镶面,前掌花纹,舒适方便,缓冲设计~考拉海购红卡会员报价409，下单三件8折，叠加下方红卡会员900-160，到手单价低至273.87，站内近期低价~", 
  "title": "Under Armour 安德玛 HOVR SLK EVO 3021461 女子运动休闲鞋 *3件 821.6元（合273.87元/件）"
 }, 
 {
  "date": "Mon, 23 Sep 2019 16:17:33", 
  "link": "https://www.smzdm.com/p/16323274/", 
  "description": "咸豆包1米Type-C线，纽曼出品。T701数据线，Type-C接口，PVC外被，线长1米，支持2A电流。京东现售价5.9元，下单两件，叠加商品页面5元白条券及6元运费券，到手价6.8元，1米Type-C线，纽曼出品，自营好价。", 
  "title": "Newmine 纽曼 T701 Type-C 数据线 1米 *2件 11.8（可使用5元白条券）"
 }
]