[
 {
  "date": "Mon, 19 Jul 2021 14:57:41", 
  "link": "https://www.smzdm.com/p/36545759/", 
  "description": "皇骑士防疫尚未结束，口罩还是刚需。京东五世同堂官方旗舰店售价25元，下单3件，参加满2件总价5折优惠，叠加领取满69-20元优惠券，实际到手价格17.5元包邮，折合1件5.83元。购买过的用户反馈：买过的三种口罩里面包装最细致，嘴部贴合最柔软，工艺用心，整体轻薄，颜色偏浅，耳带呢位置设...", 
  "title": "WELLDAY 维德 一次性医用口罩 30只装 5.83元（需买3件，需用券，共17.5元包邮）"
 }, 
 {
  "date": "Mon, 19 Jul 2021 12:49:37", 
  "link": "https://www.smzdm.com/p/36548521/", 
  "description": "唐老鸭57为肌肤建立保护屏障，淡化细纹和皱纹，均匀肤色~天猫国际官方直营现售价419元，21日拍下1件85折，领取使用APP端商品下方满300-30元美妆购物券以及妙颜社会员中心兑换满399-40元优惠券，叠加88VIP95折，到手271.84元包邮包税，好价可入～", 
  "title": "21日0点、88VIP：Elizabeth Arden 伊丽莎白·雅顿 金致导航眼部胶囊精华液 60粒+赠面胶28粒 271.84元（包邮包税，需用券）"
 }, 
 {
  "date": "Mon, 19 Jul 2021 14:57:38", 
  "link": "https://www.smzdm.com/p/36551473/", 
  "description": "藏尽心事的小拉每粒约1.15元~唯品会目前售价119元，下单1件，商品页面领取50元优惠券，到手实付69元包税包邮~", 
  "title": "goodhealth 好健康 氨糖软骨素胶囊 60粒 69元包邮包税（需用券）"
 }, 
 {
  "date": "Mon, 19 Jul 2021 14:57:36", 
  "link": "https://www.smzdm.com/p/36545518/", 
  "description": "值友1736795951低至0.46元/粒~唯品会目前售价46元，近期好价，喜欢的朋友不要错过。", 
  "title": "Healthy Care 大豆卵磷脂胶囊 100粒 46元包邮（需用券）"
 }, 
 {
  "date": "Mon, 19 Jul 2021 09:42:20", 
  "link": "https://www.smzdm.com/p/36538490/", 
  "description": "乐乐豆豆就是我时尚百搭 京东该商品目前售价69元，下单2件使用84元优惠券，叠加领取plus会员券5元，2件实付49元，折合单件到手价格24.5元，感兴趣的值友不容错过~", 
  "title": "PLUS会员：Langsha 浪莎 FA500-8 男士短袜 8双装 24.5元（需买2件，实付49元包邮，需用券）"
 }, 
 {
  "date": "Mon, 19 Jul 2021 14:57:22", 
  "link": "https://www.smzdm.com/p/36551313/", 
  "description": "美妆范儿天猫国际官方直营 正在进行进口美妆周专场，活动详情如下：活动时间：7月19日-20日抢先加购，21日-23日开始抢购；活动力度 ：部分商品参与立减活动，还可以领取店铺大额优惠券，限量抢爆款抢5折、相当于买一送一的等量优惠；兰蔻 菁纯哑光唇膏#196 到手229元，兰蔻持妆轻透粉底...", 
  "title": "促销活动：天猫国际直营 进口美妆周专场 限量抢爆款抢5折~"
 }, 
 {
  "date": "Mon, 19 Jul 2021 11:16:30", 
  "link": "https://www.smzdm.com/p/36541117/", 
  "description": "香辣味浓 劲道入味京东鳗知道生鲜旗舰店原价25.9元，现可领取满19-7元优惠券，券后单价仅18.9元包邮。感兴趣的值友可以关注一下。甄选优质鳗鱼，反复蒸煮，入味至里，色泽饱满，香辣美味，货真价实，有嚼劲。", 
  "title": "manzhidao 鳗知道 麻辣小鱼干鳗鱼丝 125g*2包 18.9元包邮（需用券）"
 }, 
 {
  "date": "Sun, 18 Jul 2021 00:16:29", 
  "link": "https://www.smzdm.com/p/36493714/", 
  "description": "pigwang499天然植物乳液，提亮肤色，紫苏水好搭档~考拉海购21日0-2点黑卡价254元，考拉海购APP内下单立减25元，折后价229元包邮包税，近期好价，喜欢可入~", 
  "title": "21日0点、黑卡会员：COSME DECORTE 黛珂 牛油果乳液 150ml 229元（包邮包税，前两个小时）"
 }, 
 {
  "date": "Mon, 19 Jul 2021 09:46:11", 
  "link": "https://www.smzdm.com/p/36538634/", 
  "description": "鞋型简约美观天猫乐卡克官方旗舰店目前售价279元，值友还可再领取100元专享券，券后此款仅179元，近期好价，库存有限，仅限今晚23点前购买，有兴趣的值友可以入手～", 
  "title": "le coq sportif 乐卡克 191229 男女情侣款魔术贴凉鞋 179元（包邮、需用券）"
 }, 
 {
  "date": "Mon, 19 Jul 2021 14:36:16", 
  "link": "https://www.smzdm.com/p/36552620/", 
  "description": "pigwang499图案可爱 超薄吸收体 京东国际该商品当前售价75元，下单3件享受8折，叠加plus会员满105元减5元优惠券，到手价170包税包邮，折合每件56.67元，近期好价~", 
  "title": "PLUS会员：moony 女宝宝拉拉裤 XL38片 56.67元（需买3件，共170元包税包邮，需用券）"
 }, 
 {
  "date": "Mon, 19 Jul 2021 12:01:44", 
  "link": "https://www.smzdm.com/p/36546367/", 
  "description": "古树精料，香醇回甘～京东隆仁古茶旗舰店目前售价108元，下单1件，领取满108元-72元优惠券，再叠加PLUS会员5元品类券，实付31元包邮。", 
  "title": "PLUS会员：隆仁古茶 2019年金芽普洱熟茶饼  357g 31元包邮（双重优惠）"
 }, 
 {
  "date": "Mon, 19 Jul 2021 14:56:39", 
  "link": "https://www.smzdm.com/p/36546464/", 
  "description": "降低驾驶眩晕感，恶劣天气也能保证视线清晰~天猫精选现售价1558元2片，领取1000元优惠券，实付558元到手，近期好价，喜欢可入~", 
  "title": "ZEISS 蔡司 1.60折射 钻立方极光膜 驾驶型镜片 *2件 558元（包邮，需用券）"
 }, 
 {
  "date": "Sun, 18 Jul 2021 18:33:41", 
  "link": "https://www.smzdm.com/p/36521629/", 
  "description": "正中靶心双出水设计 京东商城现售价2498元，下单减800元，领取30元券到手价1668元，喜欢可入~", 
  "title": "Haier 海尔 HRO4H79-2 净水器 400G 1668元包邮（双重优惠）"
 }, 
 {
  "date": "Mon, 19 Jul 2021 14:49:04", 
  "link": "https://www.smzdm.com/p/36553130/", 
  "description": "售罄专为久坐设计 居家办公极度舒适之选～天猫该商品原价1699元，满1699减200元，领取500元优惠券，到手价999元包邮。近期好价，喜欢的值友不要错过~叠加优惠券：满1699减500元", 
  "title": "UE 永艺 人体工学电脑座椅 999元（包邮）"
 }, 
 {
  "date": "Mon, 19 Jul 2021 00:30:22", 
  "link": "https://www.smzdm.com/p/36532229/", 
  "description": "值友1326645990书写顺滑，字迹清晰。天猫商城此款商品售价2.9元，近期好价，喜欢可入。", 
  "title": "M&G 晨光 本味简约系列 1支4色圆珠笔+2支中性笔 2.9元包邮"
 }, 
 {
  "date": "Mon, 19 Jul 2021 14:56:20", 
  "link": "https://www.smzdm.com/p/36549575/", 
  "description": "美观精致~京东安波尔特母婴拼购旗舰店售价19.9元，领取10元优惠券，实际到手价9.9元包邮。仙气十足，带上很有时尚感。珍珠非常牢固，大人小孩都可用。", 
  "title": "安波尔特 花朵黑白闪钻发夹 4件套 9.9元包邮（2人拼购，需用券）"
 }, 
 {
  "date": "Mon, 19 Jul 2021 14:56:11", 
  "link": "https://www.smzdm.com/p/36553184/", 
  "description": "免接电支持水桶/河流自吸，5C高倍电显锂电池京东商城现PLUS会员价358元，可领取满328元减70元优惠券，到手价288元包邮，感兴趣的值友可以关注一下。", 
  "title": "PLUS会员：XIAO SI 小巳 xs002 电动洗车器 彩盒单电 24Vf标准款 288元包邮（需用券）"
 }, 
 {
  "date": "Mon, 19 Jul 2021 14:56:11", 
  "link": "https://www.smzdm.com/p/36553227/", 
  "description": "直播小小值香草风味，醇厚香甜～什么值得买淘宝直播间售价60元，加入购物车下单减24元，88vip下单1件，实付到手价34.2元，库存有限，机会难得，喜欢的值友可以入手～直播时间:14-23点，商品优惠下播即结束，机会难得，想购买好物的值友们抓紧时间下单啦～", 
  "title": "直播专享：TERUN 天润 冰淇淋化了酸奶 整箱180gx12袋 34.2元包邮"
 }, 
 {
  "date": "Mon, 19 Jul 2021 14:56:00", 
  "link": "https://www.smzdm.com/p/36551383/", 
  "description": "藏尽心事的小拉组合装，更优惠~唯品会售价268元，页面领取70元优惠券，下单1件，实付198元包邮包税。", 
  "title": "Swisse 斯维诗 葡萄籽片180片+月见草油胶囊200粒 198元包邮包税（需用券）"
 }, 
 {
  "date": "Mon, 19 Jul 2021 14:55:36", 
  "link": "https://www.smzdm.com/p/36553052/", 
  "description": "艺术星空家居潮流装饰背景墙挂画。Decue Wu《时尚×奥迪》，此商品京东维格列艺术官方旗舰店在售，商品售价500元，近期好价，喜欢的值友可以关注哦。在意大利、德国和日本为 Vogue中国X奥迪推广A7跑车的合作项目做的城市插画，艺术家的作品充满时髦的气息，色彩饱满，构图清晰，画面没有太...", 
  "title": "Decue Wu《时尚×奥迪》系列一 14x14cm 现代插画时尚作品 500元"
 }, 
 {
  "date": "Mon, 19 Jul 2021 13:24:19", 
  "link": "https://www.smzdm.com/p/36549835/", 
  "description": "唐老鸭57色号齐全，官方补贴，柔滑液体凝胶质地，入手史低价～天猫国际官方直营21日售价329元，参加下单1件67折，使用APP端商品下方满300元减30元美妆购物券，叠加妙颜社会员中心兑换满6元减5元店铺优惠券，使用88会员95折，到手176.16元，近期好价，感兴趣的值友可入～", 
  "title": "21日0点、88VIP：sisley 希思黎 魅惑口红 3.4g 176.16元（包邮包税，需用券）"
 }, 
 {
  "date": "Mon, 19 Jul 2021 14:54:57", 
  "link": "https://www.smzdm.com/p/36544463/", 
  "description": "狗嘿嘿皮脆柔嫩~低至18.9元/次天猫麦当劳中国官方旗舰店现售价37.8元，下单1件，实付37.8元。经典美味随心选套餐，可分次兑换。", 
  "title": "McDonald's 麦当劳 麦麦脆汁鸡小食套餐随心选 2次券 37.8元"
 }, 
 {
  "date": "Mon, 19 Jul 2021 14:54:52", 
  "link": "https://www.smzdm.com/p/36546478/", 
  "description": "更强UV防护，高清透明片，超高折射率天猫精选现售价508元，领取200元优惠券，实付308元到手，赠店内康视顿230元内纯钛镜框 ，近期好价，喜欢可入~", 
  "title": "大田 大明光学 1.74超薄高清透明非球面镜片*2片+赠店内康视顿230元内纯钛镜框 308元（包邮，需用券）"
 }, 
 {
  "date": "Mon, 19 Jul 2021 12:01:43", 
  "link": "https://www.smzdm.com/p/36546438/", 
  "description": "嫩绿如新，完整柔软~京东林湖飘雪官方旗舰店售价59.9元，下单2件立减50元，可领取满61-20元券，实付49.8元包邮，折合单盒24.9元。", 
  "title": "林湖飘雪 茉莉花茶浓香毛峰级 250g 24.9元（需买2件，实付49.8元包邮）"
 }, 
 {
  "date": "Mon, 19 Jul 2021 14:52:16", 
  "link": "https://www.smzdm.com/p/36553245/", 
  "description": "小值机器人180度旋转磁吸底座，适应多种安装场景。天猫小米官方旗舰店目前售价129元，下单满减30元，到手价99元包邮，有需要的值友可以关注一下~", 
  "title": "MI 小米 2K高清 智能摄像机 标准版 99元包邮（满减）"
 }, 
 {
  "date": "Mon, 19 Jul 2021 14:54:20", 
  "link": "https://www.smzdm.com/p/36532496/", 
  "description": "终究是错付了长效保温~京东国际售价139元，会员价136元，下单两件，参加满2件总价9折优惠，领取满259-40元优惠券，叠加PLUS会员95折优惠，实际到手价格191.2元包邮，折合95.6/件。购买过的用户表示：保温杯收到了，送给老婆使用的，颜色很赞，很小巧，女生单手操作毫无压力。内部看...", 
  "title": "PLUS会员：ZOJIRUSHI 象印 SM-SE48-AL 保温杯 480ml 95.6元（需买2件，共191.2元包邮，需用券）"
 }, 
 {
  "date": "Mon, 19 Jul 2021 14:54:19", 
  "link": "https://www.smzdm.com/p/36553011/", 
  "description": "艺术星空东陵玉莲蓬耳饰 精选文玩耳坠东陵玉莲蓬耳饰，微拍堂聚宝斋世家店铺售价99元包邮，近期好价，喜欢的值友可以入手～产品：东陵玉莲蓬耳饰 尺寸：12x12mm东陵玉，学名：砂金石，亦称海洋石或东陵石，在地质学上称含铬云母石英岩。东陵石目前有绿色及红色的两种，大多不透明，偶尔部分有点半透...", 
  "title": "东陵玉莲蓬耳饰 12x12mm 天然 99元（包邮）"
 }, 
 {
  "date": "Mon, 19 Jul 2021 14:54:14", 
  "link": "https://www.smzdm.com/p/36549434/", 
  "description": "全网带货人清香纯正，醇和绵柔，口感醇厚~京东售价258元，下单2件，8折，使用499元减100元优惠券（页面领取，有券的上），共312元包邮，合一瓶156元。", 
  "title": "有券的上：董酒 百年封藏 54%vol 董香型 500ml 156元（需买2件，共312元包邮）"
 }, 
 {
  "date": "Mon, 19 Jul 2021 14:43:25", 
  "link": "https://www.smzdm.com/p/36552909/", 
  "description": "ssww0813升大容积率 24种烹饪模式 24小时随心预约 京东商城现售价146元，喜欢可入~", 
  "title": "MIJIA 米家 MDFBZ02ACM 电饭煲 3L 146元包邮"
 }, 
 {
  "date": "Sun, 18 Jul 2021 19:49:50", 
  "link": "https://www.smzdm.com/p/36523187/", 
  "description": "正中靶心贴近肌肤 5向动感刀头 快速灵活剃须 京东商城现售价499元包邮，近期好价，喜欢的值友可以看看。", 
  "title": "PHILIPS 飞利浦 S5079/04 电动剃须刀 499元包邮"
 }
]