[
 {
  "date": "Tue, 03 Sep 2019 21:16:49", 
  "link": "https://www.smzdm.com/p/15937720/", 
  "description": "小值机器人3段IH加热，备长碳内胆。京东自营优惠价799元包邮，有需要的值友不要错过。", 
  "title": "TOSHIBA 东芝 RC-7HMC IH电饭煲 2L 799元包邮"
 }, 
 {
  "date": "Tue, 03 Sep 2019 21:20:47", 
  "link": "https://www.smzdm.com/p/15930869/", 
  "description": "安全环保，结实耐用~天猫三樱居家日用旗舰店目前3合1售价9.7元，可领取3元优惠券，实付6.7元包邮到手，来到近期同款推荐最低，推荐有需要的值友关注~", 
  "title": "三樱 PE平口保鲜袋 大中小3合1 共240只 6.7元包邮（需用券）"
 }, 
 {
  "date": "Tue, 03 Sep 2019 06:37:51", 
  "link": "https://www.smzdm.com/p/15919543/", 
  "description": "thsec兼容多平台，性价比游戏手柄。京东现售价43元，下单两件享9.5折优惠，可使用15元店铺券，到手价107.55，折合35.85元/件，兼容多平台，性价比游戏手柄。什么值得批：下单8件享9.5折优惠，叠加100元优惠券，到手价226.8元，合28.35元/件，性价比再升级~", 
  "title": "BETOP 北通 蝙蝠 D2F 游戏手柄 *3件 107.55元包邮（双重优惠，合35.85元/件）"
 }, 
 {
  "date": "Tue, 03 Sep 2019 20:40:47", 
  "link": "https://www.smzdm.com/p/15937447/", 
  "description": "值友8085882406袖口系带，撞色涂鸦印花~天猫精选Lily官方旗舰店售价219元，使用50元优惠券后实付169元，有需要的值友可关注购买。叠加优惠券：50元优惠券", 
  "title": "女神超惠买：Lily 118110C7668 女士撞色长袖连衣裙 169元（需用券）"
 }, 
 {
  "date": "Mon, 02 Sep 2019 14:12:22", 
  "link": "https://www.smzdm.com/p/15908535/", 
  "description": "全程无自费。春秋旅游网现有杭州-缅甸仰光+内比都+蒲甘+曼德勒7天5晚跟团游，至10月可订，最低价2689元起/人（多班期）。国庆有团，错峰不涨价（10/5），需要的值友们抓紧时间上车。费用包含房费：缅甸4-5钻酒店；餐费：5早10正（正餐60元/人/餐）；交通：正规空调旅游车；...", 
  "title": "佛国深度游！杭州-缅甸仰光+内比都+蒲甘+曼德勒7天5晚跟团游 2689元起/人"
 }, 
 {
  "date": "Tue, 03 Sep 2019 20:52:32", 
  "link": "https://www.smzdm.com/p/15937534/", 
  "description": "春天花会开_37.04元/件，3.7元/斤。京东售价58.8元，参加满2件8折活动叠加满169-30元优惠券，下单3件实付111.12元包邮，折37.04元/件，3.7元/斤。", 
  "title": "十月稻田 五常香米 稻花香米 东北大米 5kg *3件 111.12元包邮（双重优惠）"
 }
]